troml/__init__.py
troml/classifiers.py
troml/loader.py
troml/trove-classifiers
troml/utils.py
troml/writer.py
troml-0.4.1.dist-info/WHEEL
troml-0.4.1.dist-info/entry_points.txt
troml-0.4.1.dist-info/METADATA
troml-0.4.1.dist-info/RECORD
