Metadata-Version: 2.4
Name: troml
Version: 0.4.1
Summary: Suggests classifiers for Python packages.
Keywords: python,toml,pyproject
License-Expression: MIT
Classifier: Programming Language :: Python
Classifier: Programming Language :: Python :: 3.11
Classifier: Programming Language :: Python :: 3.12
Classifier: Programming Language :: Python :: 3.13
Classifier: Programming Language :: Python :: 3.14
Classifier: Programming Language :: Python :: 3.15
Requires-Dist: packaging>=25.0
Requires-Dist: tomlkit>=0.13.3
Requires-Dist: trove-classifiers>=2025.9.11.17
Requires-Dist: typer>=0.17.4
Requires-Python: >=3.11
Project-URL: Homepage, https://github.com/adamghill/troml/
Project-URL: Repository, https://github.com/adamghill/troml.git
